CHANGELOG.rst
MANIFEST.in
README.rst
setup.cfg
setup.py
pergenie/__init__.py
pergenie/__main__.py
pergenie.egg-info/PKG-INFO
pergenie.egg-info/SOURCES.txt
pergenie.egg-info/dependency_links.txt
pergenie.egg-info/entry_points.txt
pergenie.egg-info/top_level.txt
pergenie/data/gwascatalog.pergenie.African.p
pergenie/data/gwascatalog.pergenie.Asian.p
pergenie/data/gwascatalog.pergenie.European.p
pergenie/data/gwascatalog.pergenie.unknown.p
pergenie/lib/__init__.py
pergenie/lib/parser/VCFParser.py
pergenie/lib/parser/__init__.py
pergenie/lib/parser/andmeParser.py
pergenie/lib/parser/test_VCFParser.py
pergenie/lib/parser/test_andmeParser.py
pergenie/lib/riskreport/__init__.py
pergenie/lib/riskreport/base.py
pergenie/lib/riskreport/cui.py
pergenie/lib/utils/__init__.py
pergenie/lib/utils/genome.py
test/__init__.py