Metadata-Version: 1.1
Name: pergenie
Version: 0.1.4
Summary: perGENIE is a Web/CUI application for personal genome interpretation.
Home-page: https://github.com/perGENIE/pergenie-cli
Author: Kensuke Numakura
Author-email: knmkr3gma+pip@gmail.com
License: GNU AGPLv3
Keywords: bioinformatics,personal genome
Platform: UNKNOWN
Classifier: Development Status :: 2 - Pre-Alpha
Classifier: Intended Audience :: Developers
Classifier: Intended Audience :: Education
Classifier: Intended Audience :: End Users/Desktop
Classifier: Intended Audience :: Healthcare Industry
Classifier: Intended Audience :: Information Technology
Classifier: Intended Audience :: Science/Research
Classifier: Natural Language :: English
Classifier: Natural Language :: Japanese
Classifier: Operating System :: MacOS :: MacOS X
Classifier: Operating System :: Unix
Classifier: Programming Language :: Python :: 2.6
Classifier: Programming Language :: Python :: 2.7
Classifier: Programming Language :: Python :: 2 :: Only
Classifier: Topic :: Scientific/Engineering :: Bio-Informatics
